{
  "dolls": "Dolls",
  "initial": "first",
  "first": "first",
  "foremost": "first",
  "beginning": "first",
  "next": "second",
  "second": "second",
  "following": "second",
  "another": "second",
  "thirdly": "third",
  "third": "third",
  "tertiary": "third",
  "fourthly": "fourth",
  "fourth": "fourth",
  "quarter": "fourth",
  "fifthly": "fifth",
  "fifth": "fifth",
  "quint": "fifth",
  "skateboards": "skateboards",
  "scooters": "scooters",
  "science kits": "science kits",
  "craft kits": "craft kits",
  "musical toys": "musical toys",
  "kids furniture": "kids furniture",
  "bobbleheads": "Bobbleheads",
  "building sets": "Building Sets",
  "action figures": "Action Figures",
  "electronic learning toys": "Electronic Learning Toys",
  "card games": "Card Games",
  "stuffed animals": "Stuffed Animals",
  "board games": "Board Games",
  "banners": "Banners",
  "pretend play": "Pretend Play",
  "decorations": "Decorations",
  "team sports": "Team Sports",
  "app controlled vehicles": "App Controlled Vehicles",
  "clay & dough": "Clay & Dough",
  "play sets & playground equipment": "Play Sets & Playground Equipment",
  "educational apps": "Educational Apps",
  "outdoor furniture": "Outdoor Furniture",
  "puzzles": "Puzzles",
  "craft supplies": "Craft Supplies",
  "gaming tops": "Gaming Tops",
  "drawing & painting supplies": "Drawing & Painting Supplies",
  "fidget toys": "Fidget Toys",
  "kitchen utensils & gadgets": "Kitchen Utensils & Gadgets",
  "travel accessories": "Travel Accessories",
  "bath & bathing accessories": "Bath & Bathing Accessories",
  "toys": "toys",
  "skates, skateboards and scooters": "skates, skateboards and scooters",
  "science kits and toys": "science kits and toys",
  "models and model kits": "models and model kits",
  "jigsaw puzzles": "jigsaw puzzles",
  "kids and baby": "kids and baby",
  "window treatments": "window treatments",
  "statues, bobbleheads and busts": "statues, bobbleheads and busts",
  "flash cards": "flash cards",
  "kids' furniture": "kids' furniture",
  "money banks": "money banks",
  "slumber bags": "slumber bags",
  "hobby building tools and hardware": "hobby building tools and hardware",
  "teaching clocks": "teaching clocks",
  "kids' room décor": "kids' room décor",
  "costumes": "costumes",
  "training and behavior aids": "training and behavior aids",
  "remote and app controlled vehicles and parts": "remote and app controlled vehicles and parts",
  "clothing": "clothing",
  "accessories": "accessories",
  "sorting and stacking toys": "sorting and stacking toys",
  "stuffed animals and teddy bears": "stuffed animals and teddy bears",
  "playsets": "playsets",
  "miniatures": "miniatures",
  "plush puppets": "plush puppets",
  "plush figures": "plush figures",
  "playsets and vehicles": "playsets and vehicles",
  "clay and dough": "clay and dough",
  "game accessories": "game accessories",
  "toys and game room": "toys and game room",
  "trains and accessories": "trains and accessories",
  "paper and paper crafts": "paper and paper crafts",
  "play sets and playground equipment": "play sets and playground equipment",
  "plush pillows": "plush pillows",
  "electronics": "electronics",
  "leisure sports and game room": "leisure sports and game room"
}